dashai_flux_model_package/__init__.py
dashai_flux_model_package/flux_v1_model.py
dashai_flux_model_package-0.0.4.dist-info/METADATA
dashai_flux_model_package-0.0.4.dist-info/WHEEL
dashai_flux_model_package-0.0.4.dist-info/entry_points.txt
dashai_flux_model_package-0.0.4.dist-info/RECORD
